ftd_django/__init__.py
ftd_django/helpers.py
ftd_django-0.1.9.dist-info/METADATA
ftd_django-0.1.9.dist-info/WHEEL
ftd_django-0.1.9.dist-info/top_level.txt
ftd_django-0.1.9.dist-info/RECORD
