Metadata-Version: 2.1
Name: ftd-django
Version: 0.1.9
Summary: Helper for using `ftd` as template language in your django project.
Home-page: https://github.com/FifthTry/ftd-py
Author: Amit Upadhyay
Author-email: upadhyay@gmail.com
License: UNKNOWN
Project-URL: Bug Tracker, https://github.com/FifthTry/ftd-py/issues
Platform: UNKNOWN
Requires-Python: >=3.6
Requires-Dist: ftd (>=0.1.6)
